trade_date/__init__.py
trade_date/bizd.txt
trade_date/trade_date.py
trade_date-0.0.1.dist-info/METADATA
trade_date-0.0.1.dist-info/WHEEL
trade_date-0.0.1.dist-info/top_level.txt
trade_date-0.0.1.dist-info/RECORD
